README.md
setup.py
fsdf/__init__.py
fsdf.egg-info/PKG-INFO
fsdf.egg-info/SOURCES.txt
fsdf.egg-info/dependency_links.txt
fsdf.egg-info/requires.txt
fsdf.egg-info/top_level.txt