Metadata-Version: 2.1
Name: fsdf
Version: 6.3
Summary: short namespace for function_scheduling_distributed_framework
Home-page: UNKNOWN
Author: bfzs
Author-email: m13148804508@163.com
Maintainer: ydf
Maintainer-email: m13148804508@163.com
License: BSD License
Platform: all
Classifier: Development Status :: 4 - Beta
Classifier: Operating System :: OS Independent
Classifier: Intended Audience :: Developers
Classifier: License :: OSI Approved :: BSD License
Classifier: Programming Language :: Python
Classifier: Programming Language :: Python :: Implementation
Classifier: Programming Language :: Python :: 3.6
Classifier: Topic :: Software Development :: Libraries
